servicecatalog_factory/__init__.py
servicecatalog_factory/aws.py
servicecatalog_factory/cli.py
servicecatalog_factory/constants.py
servicecatalog_factory/constants_test.py
servicecatalog_factory/core.py
servicecatalog_factory/core_test.py
servicecatalog_factory/empty.template.yaml
servicecatalog_factory/example-config-small.yaml
servicecatalog_factory/example-config.yaml
servicecatalog_factory/luigi_tasks_and_targets.py
servicecatalog_factory/schema.yaml
servicecatalog_factory/sdk.py
servicecatalog_factory/servicecatalog-factory-initialiser.template.yaml
servicecatalog_factory/servicecatalog-factory-regional.template.yaml
servicecatalog_factory/servicecatalog-factory.template.yaml
servicecatalog_factory/utils.py
servicecatalog_factory/portfolios/ccoe.yaml
servicecatalog_factory/portfolios/example-quickstart.yaml
servicecatalog_factory/portfolios/example-simple-github.yaml
servicecatalog_factory/portfolios/example-simple.yaml
servicecatalog_factory/templates/associations.j2
servicecatalog_factory/templates/constraint-launch-role-nested.template.yaml
servicecatalog_factory/templates/constraint-launch-role-parent.template.yaml
servicecatalog_factory/templates/product-cloudformation.j2
servicecatalog_factory/templates/product-terraform.j2
servicecatalog_factory/templates/terraform.template.yaml.j2
servicecatalog_factory/templates/test-action.j2
servicecatalog_factory/templates/tests/CFNNagBuildProject.j2
servicecatalog_factory/templates/tests/CloudformationRSpecProject.j2
servicecatalog_factory/templates/tests/ValidateProject.j2
aws_service_catalog_factory-0.45.0.dist-info/LICENSE
aws_service_catalog_factory-0.45.0.dist-info/METADATA
aws_service_catalog_factory-0.45.0.dist-info/NOTICE
aws_service_catalog_factory-0.45.0.dist-info/WHEEL
aws_service_catalog_factory-0.45.0.dist-info/entry_points.txt
aws_service_catalog_factory-0.45.0.dist-info/top_level.txt
aws_service_catalog_factory-0.45.0.dist-info/RECORD
